vdct2template/__init__.py
vdct2template/__main__.py
vdct2template/_version.py
vdct2template/convert.py
vdct2template/expansion.py
vdct2template/macros.py
vdct2template/regex.py
vdct2template-1.0.2.dist-info/licenses/LICENSE
vdct2template-1.0.2.dist-info/METADATA
vdct2template-1.0.2.dist-info/WHEEL
vdct2template-1.0.2.dist-info/entry_points.txt
vdct2template-1.0.2.dist-info/top_level.txt
vdct2template-1.0.2.dist-info/RECORD
